{"id":"0RI9lIluqSQ5kfBo70xG","g":["you","woman","man","look"],"u":"the-big-rule-is-that-you-must-never-get-mixed-up-dd8f8199538f","y":"qt","t":"The big rule is that you must never get mixed up with a married man - never even look sideways at another woman's fella. Boy, I really was terrific at obeying that rule, wasn't I?","B":{"id":"sWCaeNGwh7WlB3rWfJxPm2folOP2","n":"Lauren Bacall","p":"576f940ef75d"},"_B":{"id":"sWCaeNGwh7WlB3rWfJxPm2folOP2","n":"Lauren Bacall","p":"576f940ef75d"},"h":"<p class=\"bre--align-center\">The big rule is that you must never get mixed up with a married man - never even look sideways at another woman's fella. Boy, I really was terrific at obeying that rule, wasn't I?</p>"}