{"id":"gztx719voCyKDnrC4trl","g":["women","name","true","slavery"],"u":"we-say-that-slavery-has-vanished-from-european-d9fc758037fb","y":"qt","t":"We say that slavery has vanished from European civilization, but this is not true. Slavery still exists, but now it applies only to women and its name is prostitution.","B":{"id":"0smG6NV5PgN8K4bUTSi8NEkzfkO2","n":"Victor Hugo","p":"f6d472c01dd0"},"_B":{"id":"0smG6NV5PgN8K4bUTSi8NEkzfkO2","n":"Victor Hugo","p":"f6d472c01dd0"},"h":"<p class=\"bre--align-center\">We say that slavery has vanished from European civilization, but this is not true. Slavery still exists, but now it applies only to women and its name is prostitution.</p>"}