{"id":"hnRBLpIJnQbk66HgLXEw","g":["love","sleep","mom","small"],"u":"i-lived-with-my-mom-in-a-really-small-apartment-59ce75543fb3","y":"qt","t":"I lived with my mom in a really small apartment. My bedroom was like in the living room. That's why I still love to sleep on couches now.","B":{"id":"3iTSjCnhiZQBisodTQGtW5pTxHN2","n":"Alicia Keys","p":"22a30fa73197"},"_B":{"id":"3iTSjCnhiZQBisodTQGtW5pTxHN2","n":"Alicia Keys","p":"22a30fa73197"},"h":"<p class=\"ql-align-center\">I lived with my mom in a really small apartment. My bedroom was like in the living room. That's why I still love to sleep on couches now.</p>"}