{"id":"qIvmeGWKuFC2y61gFWAq","g":["sea","women","people","think"],"u":"if-i-own-a-large-part-of-scotland-i-can-turn-the-d9a6913a04c5","y":"qt","t":"If I own a large part of Scotland, I can turn the people off the land practically into the sea or across the sea. I can take women in child-bearing and throw them into the snow and leave them there. ...","B":{"id":"gaB77PcM8bhI3D6feqIdvyQUibT2","n":"George Bernard Shaw","p":"a1f1d3c4e20b"},"_B":{"id":"gaB77PcM8bhI3D6feqIdvyQUibT2","n":"George Bernard Shaw","p":"a1f1d3c4e20b"},"h":"<p class=\"ql-align-center\">If I own a large part of Scotland, I can turn the people off the land practically into the sea or across the sea. I can take women in child-bearing and throw them into the snow and leave them there. That has been done. I can do it for no better reason than I think it is better to shoot deer on the land than allow people to live on it.</p>"}