{"id":"YdwA9LZHAK2TW4lrGL4i","g":["life","me","experience","feel"],"u":"the-entertainment-industry-is-pretty-nuts-and-739f8b538a87","y":"qt","t":"The entertainment industry is pretty nuts, and having had that experience outside of it and going to university has really made a big difference. It's important to me to feel like I have my own life.","B":{"id":"g78end7ft1giWYoVfA6xtYiM1YZ2","n":"Emma Watson","p":"5909b99ece5c"},"_B":{"id":"g78end7ft1giWYoVfA6xtYiM1YZ2","n":"Emma Watson","p":"5909b99ece5c"},"h":"<p class=\"ql-align-center\">The entertainment industry is pretty nuts, and having had that experience outside of it and going to university has really made a big difference. It's important to me to feel like I have my own life.</p>"}