{"id":"aVqpJA67D7NmPdsX1gqh","g":["fish","salt","shark","ocean","meat"],"u":"most-fish-have-little-salt-in-them-sharks-9420b247e729","y":"ft","t":"Most fish have little salt in them. Sharks, however, have meat as salty as the ocean they live in. ","B":{"id":"QaeL6VPj8xS70IlYHUOIJ2jQfin1","n":"Anonymous","p":"009fbd7e8990"},"_B":{"id":"QaeL6VPj8xS70IlYHUOIJ2jQfin1","n":"Anonymous","p":"009fbd7e8990"},"h":"<p class=\"ql-align-center\">Most fish have little salt in them. Sharks, however, have meat as salty as the ocean they live in.</p>"}