{"id":"BlaUfXHlN3tuUTbkmnZg","g":["fish","vertebrates","earth","bony-skeleton"],"u":"fish-were-the-first-vertebrates-with-bony-e2f3165014cb","y":"ft","t":"Fish were the first vertebrates with bony skeletons to appear on Earth. Unlike today’s fish, early fish had no scales, fins, or jawbone, but they did have a dorsal fin. ","B":{"id":"QaeL6VPj8xS70IlYHUOIJ2jQfin1","n":"Anonymous","p":"009fbd7e8990"},"_B":{"id":"QaeL6VPj8xS70IlYHUOIJ2jQfin1","n":"Anonymous","p":"009fbd7e8990"},"h":"<p class=\"ql-align-center\">Fish were the first vertebrates with bony skeletons to appear on Earth. Unlike today’s fish, early fish had no scales, fins, or jawbone, but they did have a dorsal fin.</p>"}