{"id":"cZd4vhrlHbvIfmXN7JLE","g":["elizabeth-i","hat","female","fine","women","reign"],"u":"elizabeth-i-was-a-big-fan-of-hats-and-as-a-31487408693f","y":"ft","t":"Elizabeth I was a big fan of hats, and as a result, females who did not wear them on Sundays and public holidays were given a large fine during her reign. ","B":{"id":"QaeL6VPj8xS70IlYHUOIJ2jQfin1","n":"Anonymous","p":"009fbd7e8990"},"_B":{"id":"QaeL6VPj8xS70IlYHUOIJ2jQfin1","n":"Anonymous","p":"009fbd7e8990"},"h":"<p class=\"ql-align-center\">Elizabeth I was a big fan of hats, and as a result, females who did not wear them on Sundays and public holidays were given a large fine during her reign.</p>"}