{"id":"GAa4zuFYc0lK9uQnZxqS","g":["areographer","johann-heinrich-madler","year","observation","drew","map","mars"],"u":"in-1840-areographer-johann-heinrich-madler-8ed4f7d6fef0","y":"ft","t":"In 1840, areographer Johann Heinrich Madler combined ten years of observations and drew the first map of Mars. ","B":{"id":"QaeL6VPj8xS70IlYHUOIJ2jQfin1","n":"Anonymous","p":"009fbd7e8990"},"_B":{"id":"QaeL6VPj8xS70IlYHUOIJ2jQfin1","n":"Anonymous","p":"009fbd7e8990"},"h":"<p class=\"ql-align-center\">In 1840, areographer Johann Heinrich Madler combined ten years of observations and drew the first map of Mars.</p>"}