{"id":"hJ1GGvjaXmrk0t9kSuc1","g":["saliva"],"u":"you-could-produce-enough-saliva-in-a-YidxrLvPWaaj","y":"ft","t":"You could produce enough saliva in a year to fill two bathtubs.","_B":{"n":"Anonymous","p":"78276eab27d7"},"h":"<p><span style=\"background-color: rgb(255, 255, 255); color: rgb(34, 34, 34);\">You could produce enough&nbsp;</span><strong style=\"background-color: rgb(255, 255, 255); color: rgb(34, 34, 34);\">saliva</strong><span style=\"background-color: rgb(255, 255, 255); color: rgb(34, 34, 34);\">&nbsp;in a year to fill two bathtubs.</span></p>"}