{"id":"iqWF58ALqwc8WnxpfdKf","g":["people","studies","breakfast","calorie","egg","meal"],"u":"studies-show-that-people-who-eat-eggs-TR4rjaozPKQ0","y":"ft","t":"Studies show that people who eat eggs for breakfast are likely to consume fewer calories during other meals.","B":{"id":"QaeL6VPj8xS70IlYHUOIJ2jQfin1","n":"Anonymous","p":"009fbd7e8990"},"_B":{"id":"QaeL6VPj8xS70IlYHUOIJ2jQfin1","n":"Anonymous","p":"009fbd7e8990"},"h":"<p class=\"bre--align-center\">Studies show that people who eat eggs for breakfast are likely to consume fewer calories during other meals.</p>"}