{"id":"N3XjOYSBXrIKGS9LH1iz","g":["pisanthrophobia","trust","people","bad","past"],"u":"pisanthrophobia-is-the-fear-of-trusting-yWQ7mh2xbYlz","y":"ft","t":"Pisanthrophobia is the fear of trusting people due to bad past experiences.","B":{"id":"QaeL6VPj8xS70IlYHUOIJ2jQfin1","n":"Anonymous","p":"009fbd7e8990"},"_B":{"id":"QaeL6VPj8xS70IlYHUOIJ2jQfin1","n":"Anonymous","p":"009fbd7e8990"},"h":"<p class=\"bre--align-center\">Pisanthrophobia is the fear of trusting people due to bad past experiences.</p>"}