{"id":"SqjTXha0rfEcPVN3qaxo","g":["live","week","food","sleep","die"],"u":"you-can-live-for-weeks-without-eating-ApiQrdpb0PPg","y":"ft","t":"You can live for weeks without eating, but will most likely die after 11 days without sleep.","B":{"id":"QaeL6VPj8xS70IlYHUOIJ2jQfin1","n":"Anonymous","p":"009fbd7e8990"},"_B":{"id":"QaeL6VPj8xS70IlYHUOIJ2jQfin1","n":"Anonymous","p":"009fbd7e8990"},"h":"<p class=\"bre--align-center\">You can live for weeks without eating, but will most likely die after 11 days without sleep.</p>"}