{"id":"vYluMN3sgObCpRLmK5Mh","g":["crying","lose","weight","abdomen","cortisol","emotion"],"u":"crying-can-help-you-lose-weight-it-is-vcHm7zdbo9s9","y":"ft","t":"Crying can help you lose weight. It is because the hormones involved with high intensity emotions elevate cortisol level, which can subsequently lead to increased fat around the abdomen if they aren't ...","B":{"id":"QaeL6VPj8xS70IlYHUOIJ2jQfin1","n":"Anonymous","p":"009fbd7e8990"},"_B":{"id":"QaeL6VPj8xS70IlYHUOIJ2jQfin1","n":"Anonymous","p":"009fbd7e8990"},"h":"<p class=\"bre--align-center\">Crying can help you lose weight. It is because the hormones involved with high intensity emotions elevate cortisol level, which can subsequently lead to increased fat around the abdomen if they aren't released.</p>"}