{"id":"vZbUgXbPrMZkIqS2oPcP","g":["ayurveda","medicine"],"u":"ayurveda-medicine-is-one-of-the-worlds-tMXPd6yaCmyJ","y":"ft","t":"Ayurveda medicine is one of the world’s oldest medical systems. It originated in India more than 3,000 years ago and remains one of the country’s traditional health care systems.","h":"<p>Ayurveda medicine is one of the world’s oldest medical systems. It originated in India more than 3,000 years ago and remains one of the country’s traditional health care systems.</p>\n"}