{"id":"znJDI7kz2PBkf6o5h2WW","g":["cute","animal","picture","working","productive"],"u":"looking-at-cute-pictures-of-animals-rnEplaCyi54Z","y":"ft","t":"Looking at cute pictures of animals while working can make you more productive.","B":{"id":"QaeL6VPj8xS70IlYHUOIJ2jQfin1","n":"Anonymous","p":"009fbd7e8990"},"_B":{"id":"QaeL6VPj8xS70IlYHUOIJ2jQfin1","n":"Anonymous","p":"009fbd7e8990"},"h":"<p class=\"bre--align-center\">Looking at cute pictures of animals while working can make you more productive.</p>"}